report_guided_annotation/__init__.py
report_guided_annotation/__main__.py
report_guided_annotation/create_automatic_annotations.py
report_guided_annotation/extract_lesion_candidates.py
report_guided_annotation/parse_report.py
report_guided_annotation/py.typed
report_guided_annotation-0.3.4.dist-info/LICENSE
report_guided_annotation-0.3.4.dist-info/METADATA
report_guided_annotation-0.3.4.dist-info/WHEEL
report_guided_annotation-0.3.4.dist-info/top_level.txt
report_guided_annotation-0.3.4.dist-info/RECORD
