Metadata-Version: 2.2
Name: report_guided_annotation
Version: 0.3.4
Summary: Report Guided Annotation
Home-page: https://github.com/DIAGNijmegen/Report-Guided-Annotation
Author: Joeran Bosma
Author-email: Joeran.Bosma@radboudumc.nl
License: MIT
Project-URL: Bug Tracker, https://github.com/DIAGNijmegen/Report-Guided-Annotation/issues
Platform: unix
Platform: linux
Platform: osx
Platform: cygwin
Platform: win32
Classifier: Programming Language :: Python :: 3
Classifier: Programming Language :: Python :: 3 :: Only
Classifier: Programming Language :: Python :: 3.7
Classifier: Programming Language :: Python :: 3.8
Classifier: Programming Language :: Python :: 3.9
Classifier: Programming Language :: Python :: 3.10
Requires-Python: >=3.7
License-File: LICENSE
Requires-Dist: numpy
Requires-Dist: tqdm
Requires-Dist: SimpleITK
Requires-Dist: scipy
Provides-Extra: testing
Requires-Dist: pytest>=6.0; extra == "testing"
Requires-Dist: pytest-cov>=2.0; extra == "testing"
Requires-Dist: mypy>=0.910; extra == "testing"
Requires-Dist: flake8>=3.9; extra == "testing"
Requires-Dist: tox>=3.24; extra == "testing"
Dynamic: author-email
Dynamic: description
Dynamic: description-content-type
Dynamic: home-page
Dynamic: license
Dynamic: project-url
